{
  "_links": {
    "base": {
      "href": "https://192.168.125.1:443/rw/cfg/"
    },
    "self": {
      "href": "MMC/MMC_PROG_FLOW/instances"
    }
  },
  "_embedded": {
    "resources": [
      {
        "_links": {
          "self": {
            "href": "MMC/MMC_PROG_FLOW/instances/CallByVar"
          }
        },
        "_type": "cfg-dt-instance-li",
        "_title": "CallByVar",
        "rdonly": "true",
        "instanceid": "7377008",
        "attrib": [
          {
            "_type": "cfg-ia-t",
            "_title": "name",
            "value": "CallByVar"
          },
          {
            "_type": "cfg-ia-t",
            "_title": "param_nr",
            "value": "0"
          },
          {
            "_type": "cfg-ia-t",
            "_title": "alt_nr",
            "value": "0"
          },
          {
            "_type": "cfg-ia-t",
            "_title": "instr_name",
            "value": ""
          },
          {
            "_type": "cfg-ia-t",
            "_title": "only_mec_task",
            "value": "false"
          }
        ]
      },
      {
        "_links": {
          "self": {
            "href": "MMC/MMC_PROG_FLOW/instances/IF"
          }
        },
        "_type": "cfg-dt-instance-li",
        "_title": "IF",
        "rdonly": "true",
        "instanceid": "7141696",
        "attrib": [
          {
            "_type": "cfg-ia-t",
            "_title": "name",
            "value": "IF"
          },
          {
            "_type": "cfg-ia-t",
            "_title": "param_nr",
            "value": "0"
          },
          {
            "_type": "cfg-ia-t",
            "_title": "alt_nr",
            "value": "0"
          },
          {
            "_type": "cfg-ia-t",
            "_title": "instr_name",
            "value": ""
          },
          {
            "_type": "cfg-ia-t",
            "_title": "only_mec_task",
            "value": "false"
          }
        ]
      },
      {
        "_links": {
          "self": {
            "href": "MMC/MMC_PROG_FLOW/instances/WHILE"
          }
        },
        "_type": "cfg-dt-instance-li",
        "_title": "WHILE",
        "rdonly": "true",
        "instanceid": "7141424",
        "attrib": [
          {
            "_type": "cfg-ia-t",
            "_title": "name",
            "value": "WHILE"
          },
          {
            "_type": "cfg-ia-t",
            "_title": "param_nr",
            "value": "0"
          },
          {
            "_type": "cfg-ia-t",
            "_title": "alt_nr",
            "value": "0"
          },
          {
            "_type": "cfg-ia-t",
            "_title": "instr_name",
            "value": ""
          },
          {
            "_type": "cfg-ia-t",
            "_title": "only_mec_task",
            "value": "false"
          }
        ]
      },
      {
        "_links": {
          "self": {
            "href": "MMC/MMC_PROG_FLOW/instances/FOR"
          }
        },
        "_type": "cfg-dt-instance-li",
        "_title": "FOR",
        "rdonly": "true",
        "instanceid": "7141152",
        "attrib": [
          {
            "_type": "cfg-ia-t",
            "_title": "name",
            "value": "FOR"
          },
          {
            "_type": "cfg-ia-t",
            "_title": "param_nr",
            "value": "0"
          },
          {
            "_type": "cfg-ia-t",
            "_title": "alt_nr",
            "value": "0"
          },
          {
            "_type": "cfg-ia-t",
            "_title": "instr_name",
            "value": ""
          },
          {
            "_type": "cfg-ia-t",
            "_title": "only_mec_task",
            "value": "false"
          }
        ]
      },
      {
        "_links": {
          "self": {
            "href": "MMC/MMC_PROG_FLOW/instances/TEST"
          }
        },
        "_type": "cfg-dt-instance-li",
        "_title": "TEST",
        "rdonly": "true",
        "instanceid": "7140880",
        "attrib": [
          {
            "_type": "cfg-ia-t",
            "_title": "name",
            "value": "TEST"
          },
          {
            "_type": "cfg-ia-t",
            "_title": "param_nr",
            "value": "0"
          },
          {
            "_type": "cfg-ia-t",
            "_title": "alt_nr",
            "value": "0"
          },
          {
            "_type": "cfg-ia-t",
            "_title": "instr_name",
            "value": ""
          },
          {
            "_type": "cfg-ia-t",
            "_title": "only_mec_task",
            "value": "false"
          }
        ]
      },
      {
        "_links": {
          "self": {
            "href": "MMC/MMC_PROG_FLOW/instances/GOTO"
          }
        },
        "_type": "cfg-dt-instance-li",
        "_title": "GOTO",
        "rdonly": "true",
        "instanceid": "7140608",
        "attrib": [
          {
            "_type": "cfg-ia-t",
            "_title": "name",
            "value": "GOTO"
          },
          {
            "_type": "cfg-ia-t",
            "_title": "param_nr",
            "value": "0"
          },
          {
            "_type": "cfg-ia-t",
            "_title": "alt_nr",
            "value": "0"
          },
          {
            "_type": "cfg-ia-t",
            "_title": "instr_name",
            "value": ""
          },
          {
            "_type": "cfg-ia-t",
            "_title": "only_mec_task",
            "value": "false"
          }
        ]
      },
      {
        "_links": {
          "self": {
            "href": "MMC/MMC_PROG_FLOW/instances/BREAK"
          }
        },
        "_type": "cfg-dt-instance-li",
        "_title": "BREAK",
        "rdonly": "true",
        "instanceid": "7140336",
        "attrib": [
          {
            "_type": "cfg-ia-t",
            "_title": "name",
            "value": "BREAK"
          },
          {
            "_type": "cfg-ia-t",
            "_title": "param_nr",
            "value": "0"
          },
          {
            "_type": "cfg-ia-t",
            "_title": "alt_nr",
            "value": "0"
          },
          {
            "_type": "cfg-ia-t",
            "_title": "instr_name",
            "value": ""
          },
          {
            "_type": "cfg-ia-t",
            "_title": "only_mec_task",
            "value": "false"
          }
        ]
      },
      {
        "_links": {
          "self": {
            "href": "MMC/MMC_PROG_FLOW/instances/CONTINUE"
          }
        },
        "_type": "cfg-dt-instance-li",
        "_title": "CONTINUE",
        "rdonly": "true",
        "instanceid": "7140064",
        "attrib": [
          {
            "_type": "cfg-ia-t",
            "_title": "name",
            "value": "CONTINUE"
          },
          {
            "_type": "cfg-ia-t",
            "_title": "param_nr",
            "value": "0"
          },
          {
            "_type": "cfg-ia-t",
            "_title": "alt_nr",
            "value": "0"
          },
          {
            "_type": "cfg-ia-t",
            "_title": "instr_name",
            "value": ""
          },
          {
            "_type": "cfg-ia-t",
            "_title": "only_mec_task",
            "value": "false"
          }
        ]
      },
      {
        "_links": {
          "self": {
            "href": "MMC/MMC_PROG_FLOW/instances/ProcCall"
          }
        },
        "_type": "cfg-dt-instance-li",
        "_title": "ProcCall",
        "rdonly": "true",
        "instanceid": "7139792",
        "attrib": [
          {
            "_type": "cfg-ia-t",
            "_title": "name",
            "value": "ProcCall"
          },
          {
            "_type": "cfg-ia-t",
            "_title": "param_nr",
            "value": "0"
          },
          {
            "_type": "cfg-ia-t",
            "_title": "alt_nr",
            "value": "0"
          },
          {
            "_type": "cfg-ia-t",
            "_title": "instr_name",
            "value": ""
          },
          {
            "_type": "cfg-ia-t",
            "_title": "only_mec_task",
            "value": "false"
          }
        ]
      },
      {
        "_links": {
          "self": {
            "href": "MMC/MMC_PROG_FLOW/instances/Label"
          }
        },
        "_type": "cfg-dt-instance-li",
        "_title": "Label",
        "rdonly": "true",
        "instanceid": "7139520",
        "attrib": [
          {
            "_type": "cfg-ia-t",
            "_title": "name",
            "value": "Label"
          },
          {
            "_type": "cfg-ia-t",
            "_title": "param_nr",
            "value": "0"
          },
          {
            "_type": "cfg-ia-t",
            "_title": "alt_nr",
            "value": "0"
          },
          {
            "_type": "cfg-ia-t",
            "_title": "instr_name",
            "value": ""
          },
          {
            "_type": "cfg-ia-t",
            "_title": "only_mec_task",
            "value": "false"
          }
        ]
      },
      {
        "_links": {
          "self": {
            "href": "MMC/MMC_PROG_FLOW/instances/RETURN"
          }
        },
        "_type": "cfg-dt-instance-li",
        "_title": "RETURN",
        "rdonly": "true",
        "instanceid": "7139248",
        "attrib": [
          {
            "_type": "cfg-ia-t",
            "_title": "name",
            "value": "RETURN"
          },
          {
            "_type": "cfg-ia-t",
            "_title": "param_nr",
            "value": "0"
          },
          {
            "_type": "cfg-ia-t",
            "_title": "alt_nr",
            "value": "0"
          },
          {
            "_type": "cfg-ia-t",
            "_title": "instr_name",
            "value": ""
          },
          {
            "_type": "cfg-ia-t",
            "_title": "only_mec_task",
            "value": "false"
          }
        ]
      },
      {
        "_links": {
          "self": {
            "href": "MMC/MMC_PROG_FLOW/instances/EXIT"
          }
        },
        "_type": "cfg-dt-instance-li",
        "_title": "EXIT",
        "rdonly": "true",
        "instanceid": "7138976",
        "attrib": [
          {
            "_type": "cfg-ia-t",
            "_title": "name",
            "value": "EXIT"
          },
          {
            "_type": "cfg-ia-t",
            "_title": "param_nr",
            "value": "0"
          },
          {
            "_type": "cfg-ia-t",
            "_title": "alt_nr",
            "value": "0"
          },
          {
            "_type": "cfg-ia-t",
            "_title": "instr_name",
            "value": ""
          },
          {
            "_type": "cfg-ia-t",
            "_title": "only_mec_task",
            "value": "false"
          }
        ]
      },
      {
        "_links": {
          "self": {
            "href": "MMC/MMC_PROG_FLOW/instances/Compact%20IF"
          }
        },
        "_type": "cfg-dt-instance-li",
        "_title": "Compact IF",
        "rdonly": "true",
        "instanceid": "7138704",
        "attrib": [
          {
            "_type": "cfg-ia-t",
            "_title": "name",
            "value": "Compact IF"
          },
          {
            "_type": "cfg-ia-t",
            "_title": "param_nr",
            "value": "0"
          },
          {
            "_type": "cfg-ia-t",
            "_title": "alt_nr",
            "value": "0"
          },
          {
            "_type": "cfg-ia-t",
            "_title": "instr_name",
            "value": ""
          },
          {
            "_type": "cfg-ia-t",
            "_title": "only_mec_task",
            "value": "false"
          }
        ]
      }
    ]
  }
}